interpylate/BiLinearRegularGridInterpolator.py
interpylate/LinearRegularGridInterpolator.py
interpylate/NLinearRegularGridInterpolator.py
interpylate/NLinearRegularGridInterpolatorLarge.py
interpylate/TriLinearRegularGridInterpolator.py
interpylate/__init__.py
interpylate-1.0.0.dist-info/LICENSE.txt
interpylate-1.0.0.dist-info/METADATA
interpylate-1.0.0.dist-info/WHEEL
interpylate-1.0.0.dist-info/top_level.txt
interpylate-1.0.0.dist-info/RECORD
