Metadata-Version: 2.1
Name: interpylate
Version: 1.0.0
Summary: A package for N-linear regular grid interpolation
Home-page: https://github.com/Dorian210/interpylate
Author: Dorian Bichet
Author-email: dbichet@insa-toulouse.fr
License: UNKNOWN
Platform: UNKNOWN
Classifier: Programming Language :: Python :: 3
Classifier: Operating System :: OS Independent
Classifier: License :: OSI Approved :: CEA CNRS Inria Logiciel Libre License, version 2.1 (CeCILL-2.1)
Requires-Dist: numba
Requires-Dist: numpy
